mozartpy/__init__.py
mozartpy/dataconverter.py
mozartpy/modelreader.py
mozartpy/mozartsilent.py
mozartpy/scenarioreader.py
mozartpy/servicehelper.py
mozartpy/netcore/Microsoft.Data.Sqlite.dll
mozartpy/netcore/Microsoft.Extensions.Configuration.Abstractions.dll
mozartpy/netcore/Microsoft.Extensions.Configuration.Binder.dll
mozartpy/netcore/Microsoft.Extensions.Configuration.FileExtensions.dll
mozartpy/netcore/Microsoft.Extensions.Configuration.Json.dll
mozartpy/netcore/Microsoft.Extensions.Configuration.dll
mozartpy/netcore/Microsoft.Extensions.DependencyInjection.Abstractions.dll
mozartpy/netcore/Microsoft.Extensions.DependencyInjection.dll
mozartpy/netcore/Microsoft.Extensions.DependencyModel.dll
mozartpy/netcore/Microsoft.Extensions.FileProviders.Abstractions.dll
mozartpy/netcore/Microsoft.Extensions.FileProviders.Physical.dll
mozartpy/netcore/Microsoft.Extensions.FileSystemGlobbing.dll
mozartpy/netcore/Microsoft.Extensions.Logging.Abstractions.dll
mozartpy/netcore/Microsoft.Extensions.Logging.Configuration.dll
mozartpy/netcore/Microsoft.Extensions.Logging.Console.dll
mozartpy/netcore/Microsoft.Extensions.Logging.dll
mozartpy/netcore/Microsoft.Extensions.Options.ConfigurationExtensions.dll
mozartpy/netcore/Microsoft.Extensions.Options.dll
mozartpy/netcore/Microsoft.Extensions.Primitives.dll
mozartpy/netcore/Microsoft.Identity.Client.dll
mozartpy/netcore/Mozart.CodeDom.dll
mozartpy/netcore/Mozart.CodeDom.pdb
mozartpy/netcore/Mozart.Data.Access.dll
mozartpy/netcore/Mozart.Data.Access.pdb
mozartpy/netcore/Mozart.Data.Entity.dll
mozartpy/netcore/Mozart.Data.Entity.pdb
mozartpy/netcore/Mozart.DataActions.dll
mozartpy/netcore/Mozart.DataActions.pdb
mozartpy/netcore/Mozart.Distributions.dll
mozartpy/netcore/Mozart.Distributions.pdb
mozartpy/netcore/Mozart.DocComments.dll
mozartpy/netcore/Mozart.DocComments.pdb
mozartpy/netcore/Mozart.Encryption.dll
mozartpy/netcore/Mozart.Encryption.pdb
mozartpy/netcore/Mozart.Enterprise.dll
mozartpy/netcore/Mozart.Enterprise.pdb
mozartpy-1.0.1.dist-info/METADATA
mozartpy-1.0.1.dist-info/WHEEL
mozartpy-1.0.1.dist-info/top_level.txt
mozartpy-1.0.1.dist-info/RECORD
