Metadata-Version: 2.1
Name: mozartpy
Version: 1.0.1
Summary: Anaylize for Mozart Data
Home-page: https://www.vms-solutions.com/en/
Author: VMS Solutions
Author-email: support@vms-solutions.com
License: Ms-PL
Platform: UNKNOWN
Classifier: Programming Language :: Python :: 3
Classifier: License :: OSI Approved :: MIT License
Classifier: Operating System :: OS Independent
Requires-Python: >=3.6
Requires-Dist: pythonnet>=2.5.2
Requires-Dist: zeep
Requires-Dist: tqdm
Requires-Dist: pandas
Requires-Dist: multipledispatch
Requires-Dist: matplotlib
Requires-Dist: py7zr
Requires-Dist: requests
